{
  "usab_id": "1020427",
  "date": "2023-12-01",
  "categories": [
    {
      "category": "XD U17",
      "ranking_points": 3945,
      "rank": 137,
      "tournaments": [
        {
          "tournament": "2023 MBC MIDWEST OPEN LOCAL CHAMPIONSHIPS",
          "position": "1",
          "points": "1620"
        },
        {
          "tournament": "2023 YONEX SPBA MIDWEST OPEN REGIONAL CHAMPIONSHIPS",
          "position": "9-16",
          "points": "1166"
        },
        {
          "tournament": "2022 EGRET MIDWEST CLOSED REGIONAL CHAMPIONSHIPS",
          "position": "5-8",
          "points": "1013"
        },
        {
          "tournament": "2023 SOUTH FRISCO OPEN REGIONAL CHAMPIONSHIPS",
          "position": "65-128",
          "points": "146"
        }
      ]
    },
    {
      "category": "XD U15",
      "ranking_points": 1312,
      "rank": 163,
      "tournaments": [
        {
          "tournament": "2023 YONEX SPBA MIDWEST OPEN REGIONAL CHAMPIONSHIPS",
          "position": "9-16",
          "points": "1166"
        },
        {
          "tournament": "2023 SOUTH FRISCO OPEN REGIONAL CHAMPIONSHIPS",
          "position": "65-128",
          "points": "146"
        }
      ]
    },
    {
      "category": "GS U17",
      "ranking_points": 2682,
      "rank": 85,
      "tournaments": [
        {
          "tournament": "2023 MBC MIDWEST OPEN LOCAL CHAMPIONSHIPS",
          "position": "3",
          "points": "1377"
        },
        {
          "tournament": "2022 EGRET MIDWEST CLOSED REGIONAL CHAMPIONSHIPS",
          "position": "5-8",
          "points": "1013"
        },
        {
          "tournament": "2023 SOUTH FRISCO OPEN REGIONAL CHAMPIONSHIPS",
          "position": "65-128",
          "points": "146"
        },
        {
          "tournament": "2023 YONEX SPBA MIDWEST OPEN REGIONAL CHAMPIONSHIPS",
          "position": "65-128",
          "points": "146"
        }
      ]
    },
    {
      "category": "GS U15",
      "ranking_points": 292,
      "rank": 139,
      "tournaments": [
        {
          "tournament": "2023 SOUTH FRISCO OPEN REGIONAL CHAMPIONSHIPS",
          "position": "65-128",
          "points": "146"
        },
        {
          "tournament": "2023 YONEX SPBA MIDWEST OPEN REGIONAL CHAMPIONSHIPS",
          "position": "65-128",
          "points": "146"
        }
      ]
    },
    {
      "category": "GD U17",
      "ranking_points": 4016,
      "rank": 92,
      "tournaments": [
        {
          "tournament": "2022 EGRET MIDWEST CLOSED REGIONAL CHAMPIONSHIPS",
          "position": "3",
          "points": "1377"
        },
        {
          "tournament": "2023 YONEX SPBA MIDWEST OPEN REGIONAL CHAMPIONSHIPS",
          "position": "9-16",
          "points": "1166"
        },
        {
          "tournament": "2023 MBC MIDWEST OPEN LOCAL CHAMPIONSHIPS",
          "position": "3",
          "points": "744"
        },
        {
          "tournament": "2023 SOUTH FRISCO OPEN REGIONAL CHAMPIONSHIPS",
          "position": "17-32",
          "points": "729"
        }
      ]
    },
    {
      "category": "GD U15",
      "ranking_points": 2639,
      "rank": 79,
      "tournaments": [
        {
          "tournament": "2023 YONEX SPBA MIDWEST OPEN REGIONAL CHAMPIONSHIPS",
          "position": "9-16",
          "points": "1166"
        },
        {
          "tournament": "2023 MBC MIDWEST OPEN LOCAL CHAMPIONSHIPS",
          "position": "3",
          "points": "744"
        },
        {
          "tournament": "2023 SOUTH FRISCO OPEN REGIONAL CHAMPIONSHIPS",
          "position": "17-32",
          "points": "729"
        }
      ]
    }
  ],
  "name": "Aditi Gummadi",
  "year_of_birth": null,
  "gender": "XD"
}