{
  "usab_id": "1020476",
  "date": "2025-10-31",
  "categories": [
    {
      "category": "BS U19",
      "ranking_points": 14260,
      "rank": 39,
      "tournaments": [
        {
          "tournament": "2025 YONEX U.S. JUNIOR NATIONAL CHAMPIONSHIPS",
          "position": "9 to 12",
          "points": "4860"
        },
        {
          "tournament": "2025 YONEX BELLEVUE NORTHWEST OPEN REGIONAL CHAMPIONSHIPS",
          "position": "9 to 16",
          "points": "4000"
        },
        {
          "tournament": "2024 SGVBC SoCal Closed Regional Championships",
          "position": "1",
          "points": "3000"
        },
        {
          "tournament": "2025 YONEX DAVE FREEMAN JUNIOR OPEN LOCAL CHAMPIONSHIPS",
          "position": "4",
          "points": "2400"
        }
      ]
    },
    {
      "category": "BS U17",
      "ranking_points": 4860,
      "rank": 68,
      "tournaments": [
        {
          "tournament": "2025 YONEX U.S. JUNIOR NATIONAL CHAMPIONSHIPS",
          "position": "9 to 12",
          "points": "4860"
        }
      ]
    },
    {
      "category": "BD U19",
      "ranking_points": 16200,
      "rank": 52,
      "tournaments": [
        {
          "tournament": "2025 YONEX U.S. JUNIOR NATIONAL CHAMPIONSHIPS",
          "position": "2",
          "points": "9720"
        },
        {
          "tournament": "2024 SGVBC SoCal Closed Regional Championships",
          "position": "2",
          "points": "2700"
        },
        {
          "tournament": "2025 YONEX BELLEVUE NORTHWEST OPEN REGIONAL CHAMPIONSHIPS",
          "position": "9 to 16",
          "points": "2160"
        },
        {
          "tournament": "2025 YONEX DAVE FREEMAN JUNIOR OPEN LOCAL CHAMPIONSHIPS",
          "position": "1",
          "points": "1620"
        }
      ]
    },
    {
      "category": "BD U17",
      "ranking_points": 13500,
      "rank": 24,
      "tournaments": [
        {
          "tournament": "2025 YONEX U.S. JUNIOR NATIONAL CHAMPIONSHIPS",
          "position": "2",
          "points": "9720"
        },
        {
          "tournament": "2025 YONEX BELLEVUE NORTHWEST OPEN REGIONAL CHAMPIONSHIPS",
          "position": "9 to 16",
          "points": "2160"
        },
        {
          "tournament": "2025 YONEX DAVE FREEMAN JUNIOR OPEN LOCAL CHAMPIONSHIPS",
          "position": "1",
          "points": "1620"
        }
      ]
    },
    {
      "category": "XD U19",
      "ranking_points": 17350,
      "rank": 38,
      "tournaments": [
        {
          "tournament": "2025 YONEX U.S. JUNIOR NATIONAL CHAMPIONSHIPS",
          "position": "3",
          "points": "9180"
        },
        {
          "tournament": "2025 YONEX BELLEVUE NORTHWEST OPEN REGIONAL CHAMPIONSHIPS",
          "position": "9 to 16",
          "points": "4000"
        },
        {
          "tournament": "2024 SGVBC SoCal Closed Regional Championships",
          "position": "3",
          "points": "2550"
        },
        {
          "tournament": "2025 YONEX DAVE FREEMAN JUNIOR OPEN LOCAL CHAMPIONSHIPS",
          "position": "1",
          "points": "1620"
        }
      ]
    },
    {
      "category": "XD U17",
      "ranking_points": 10800,
      "rank": 42,
      "tournaments": [
        {
          "tournament": "2025 YONEX U.S. JUNIOR NATIONAL CHAMPIONSHIPS",
          "position": "3",
          "points": "9180"
        },
        {
          "tournament": "2025 YONEX DAVE FREEMAN JUNIOR OPEN LOCAL CHAMPIONSHIPS",
          "position": "1",
          "points": "1620"
        }
      ]
    }
  ],
  "name": "Mihir Thaha",
  "year_of_birth": null,
  "gender": "M",
  "year_of_birth_inferred": 2009,
  "year_of_birth_confidence": "confirmed"
}