{
  "usab_id": "534531",
  "date": "2025-04-01",
  "categories": [
    {
      "category": "XD U17",
      "ranking_points": 1188,
      "rank": 240,
      "tournaments": [
        {
          "tournament": "2025 AUSTIN BADMINTON LEANDER SOUTH CLOSED REGIONAL CHAMPIONSHIPS",
          "position": "9 to 16",
          "points": "648"
        },
        {
          "tournament": "2025 YONEX DFW BADMINTON LEWISVILLE SOUTH OPEN REGIONAL CHAMPIONSHIPS & SELECTION EVENT FOR 2025 SHO",
          "position": "33-64",
          "points": "540"
        }
      ]
    },
    {
      "category": "GS U17",
      "ranking_points": 1998,
      "rank": 92,
      "tournaments": [
        {
          "tournament": "2025 YONEX DFW BADMINTON LEWISVILLE SOUTH OPEN REGIONAL CHAMPIONSHIPS & SELECTION EVENT FOR 2025 SHO",
          "position": "17-32",
          "points": "1350"
        },
        {
          "tournament": "2025 AUSTIN BADMINTON LEANDER SOUTH CLOSED REGIONAL CHAMPIONSHIPS",
          "position": "9 to 16",
          "points": "648"
        }
      ]
    },
    {
      "category": "GD U17",
      "ranking_points": 3173,
      "rank": 102,
      "tournaments": [
        {
          "tournament": "2025 YONEX DFW BADMINTON LEWISVILLE SOUTH OPEN REGIONAL CHAMPIONSHIPS & SELECTION EVENT FOR 2025 SHO",
          "position": "9 to 16",
          "points": "2160"
        },
        {
          "tournament": "2025 AUSTIN BADMINTON LEANDER SOUTH CLOSED REGIONAL CHAMPIONSHIPS",
          "position": "5 to 8",
          "points": "1013"
        }
      ]
    }
  ],
  "name": "Varshini Thirupathi Pandiaraj",
  "year_of_birth": null,
  "gender": "F"
}