{
  "usab_id": "2034559",
  "date": "2024-01-01",
  "categories": [
    {
      "category": "BS U19",
      "ranking_points": 18500,
      "rank": 15,
      "tournaments": [
        {
          "tournament": "2023 YONEX U.S. JUNIOR NATIONAL CHAMPIONSHIPS",
          "position": "7-8",
          "points": "11000"
        },
        {
          "tournament": "2023 ARENA SOCAL OPEN REGIONAL CHAMPIONSHIPS & SELECTION EVENT FOR 2023 SHONAI INVITATIONAL",
          "position": "9-16",
          "points": "4000"
        },
        {
          "tournament": "2023 YONEX CBA NORCAL OPEN REGIONAL CHAMPIONSHIPS",
          "position": "17-32",
          "points": "2500"
        },
        {
          "tournament": "2023 SOUTH FRISCO OPEN REGIONAL CHAMPIONSHIPS",
          "position": "33-64",
          "points": "1000"
        }
      ]
    },
    {
      "category": "BD U19",
      "ranking_points": 44750,
      "rank": 1,
      "tournaments": [
        {
          "tournament": "2023 YONEX U.S. JUNIOR NATIONAL CHAMPIONSHIPS",
          "position": "1",
          "points": "20000"
        },
        {
          "tournament": "2023 SOUTH FRISCO OPEN REGIONAL CHAMPIONSHIPS",
          "position": "1",
          "points": "10000"
        },
        {
          "tournament": "2023 YONEX CBA NORCAL OPEN REGIONAL CHAMPIONSHIPS",
          "position": "3",
          "points": "8500"
        },
        {
          "tournament": "2023 ARENA SOCAL OPEN REGIONAL CHAMPIONSHIPS & SELECTION EVENT FOR 2023 SHONAI INVITATIONAL",
          "position": "5-8",
          "points": "6250"
        }
      ]
    },
    {
      "category": "XD U19",
      "ranking_points": 31500,
      "rank": 8,
      "tournaments": [
        {
          "tournament": "2023 YONEX U.S. JUNIOR NATIONAL CHAMPIONSHIPS",
          "position": "5",
          "points": "15000"
        },
        {
          "tournament": "2023 YONEX CBA NORCAL OPEN REGIONAL CHAMPIONSHIPS",
          "position": "1",
          "points": "10000"
        },
        {
          "tournament": "2023 ARENA SOCAL OPEN REGIONAL CHAMPIONSHIPS & SELECTION EVENT FOR 2023 SHONAI INVITATIONAL",
          "position": "9-16",
          "points": "4000"
        },
        {
          "tournament": "2023 SOUTH FRISCO OPEN REGIONAL CHAMPIONSHIPS",
          "position": "17-32",
          "points": "2500"
        }
      ]
    }
  ],
  "name": "Weslie Chen",
  "year_of_birth": null,
  "gender": "M"
}