{"name": "Xintong Jiang", "gender": "Female", "yob": 2012, "rankings": [], "career": "18 tournaments, 38-51 (43%)", "progression": ["2023-12-01: GD U13 #58, GS U13 #56, XD U13 #140", "2025-02-01: GD U15 #92, GS U15 #87, XD U15 #155"], "recent": ["                     2023 YONEX NorCal ORC 1W-3L", "                     2023 YONEX SoCal CRC 5W-3L", "                     2025 YONEX SOCAL ORC 0W-1L", "                     2022 SoCal CRC 7W-0L", "                     2024 YONEX NORTHWEST ORC 1W-2L", "                     2022 SoCal Arena CRC 1W-8L", "                     2021 SoCal ORC 0W-2L", "                     2024 YONEX SoCal ORC & SHONAI SELECTION EVENT 5W-3L", "                     2024 DAVE FREEMAN JR. OLC 4W-2L", "                     2022 NorCal ORC 6W-2L"], "titles": ["GS U11 at 2022 SoCal CRC", "XD U11 at 2022 SoCal CRC", "GD U13 at 2024 DAVE FREEMAN JR. OLC"], "runner_ups": [], "partners": ["Shivani Ramakrishnan (10 matches)", "Ethan Yip Ly (9 matches)", "Enming Cao (7 matches)", "Linus Yong (6 matches)", "Haziqa H Mathani (3 matches)"]}