{"name": "Fahim Mougamadou", "gender": "Male", "yob": 2011, "rankings": [], "career": "6 tournaments, 11-17 (39%)", "progression": ["2023-12-01: BD U15 #92, BS U15 #89, XD U15 #207"], "recent": ["                     2023 South OLC 1W-2L", "                     2023 South ORC 0W-2L", "                     2022 Yonex Northeast ORC 4W-3L", "                     2023 NE OLC 2W-3L", "                     2023 South CRC 1W-5L", "                     2023 Midwest ORC 3W-2L"], "titles": [], "runner_ups": [], "partners": ["Adithya S Burisetty (12 matches)", "Charvi Murali (2 matches)", "Netra Madhusudhan (1 matches)", "Mark w Wu (1 matches)"]}