{"name": "Drishik Ankem", "gender": "Male", "yob": 2012, "rankings": [], "career": "3 tournaments, 8-10 (44%)", "progression": ["2023-12-01: BD U13 #123, BS U13 #158, XD U13 #204"], "recent": ["                     2024 South OLC 4W-3L", "                     2023 South OLC 1W-3L", "                     2023 South CRC 3W-4L"], "titles": [], "runner_ups": ["BD U15 at 2024 South OLC"], "partners": ["Ayaaz Muhammed Baig (4 matches)", "Sankeerthi Marasani (3 matches)", "Vihaan s Vinay (3 matches)", "Sajith Kamal (2 matches)", "Meghana Pandiri (2 matches)"]}