{"name": "Irene Jiang", "gender": "Female", "yob": 2015, "rankings": ["GS U13 #157 (291pts)", "GS U15 #334 (291pts)", "GS U17 #485 (291pts)", "GS U19 #577 (291pts)", "GD U13 #127 (590pts)", "GD U15 #264 (590pts)", "GD U17 #422 (590pts)", "GD U19 #504 (590pts)", "XD U13 #276 (348pts)", "XD U15 #567 (348pts)", "XD U17 #817 (348pts)", "XD U19 #982 (348pts)"], "career": "4 tournaments, 1-19 (5%)", "progression": ["2025-02-01: GS U11 #45, XD U11 #69", "2026-03-01: GD U13 #122, GS U13 #117, XD U13 #245"], "recent": ["                     2024 SOCAL CRC 0W-4L", "Feb 20 to Feb 22     2026 DAVE FREEMAN JR. SOCAL OLC 0W-6L", "                     2025 YONEX SOCAL ORC 0W-2L", "                     2025 DAVE FREEMAN JR. SOCAL OLC 1W-7L"], "titles": [], "runner_ups": [], "partners": ["Jayden Chen (5 matches)", "Madison Yerim Kim (4 matches)", "Emily Yunfan Xu (4 matches)", "Eden Wong (1 matches)"]}