{"name": "Aadya Yanamandra", "gender": "Female", "yob": 2015, "rankings": ["GS U13 #12 (3655pts)", "GS U15 #37 (3655pts)", "GS U17 #93 (3655pts)", "GS U19 #150 (3655pts)", "GD U13 #8 (4398pts)", "GD U15 #49 (4398pts)", "GD U17 #119 (4398pts)", "GD U19 #181 (4398pts)", "XD U13 #11 (3876pts)", "XD U15 #59 (3876pts)", "XD U17 #162 (3876pts)", "XD U19 #280 (3876pts)"], "career": "15 tournaments, 82-46 (64%)", "progression": ["2025-02-01: GD U11 #7, GS U11 #4, XD U11 #25", "2026-03-01: GD U13 #8, GS U13 #12, XD U13 #11"], "recent": ["Jan 17 to Jan 19     2026 YONEX ARENA SOCAL ORC 0W-3L", "Feb 14 to Feb 16     2026 YONEX DFW BADMINTON SOUTH ORC 7W-3L", "Jan 3 to Jan 4       2026 WAYSIDE NE CRC 5W-3L", "                     2025 YONEX LIBC NORTHEAST ORC 7W-2L", "                     2025 YONEX MIDWEST ORC 12W-2L", "                     2025 YONEX SOCAL ORC 4W-5L", "                     2025 YONEX U.S. JUNIOR NATIONAL CHAMPIONSHIPS 12W-3L", "                     2025 YONEX SYNERGY NORCAL ORC 8W-3L", "                     2025 YONEX SOUTH ORC 9W-3L", "                     2025 YONEX BELLEVUE NORTHWEST ORC 4W-3L"], "titles": ["GS U11 at 2025 YONEX LIBC NORTHEAST ORC", "GD U11 at 2025 YONEX MIDWEST ORC", "GD U13 at 2026 WAYSIDE NE CRC", "GS U11 at 2025 NE OLC"], "runner_ups": ["GS U11 at 2025 YONEX MIDWEST ORC", "GS U13 at 2026 WAYSIDE NE CRC", "GS U11 at 2025 YONEX BELLEVUE NORTHWEST ORC"], "partners": ["Boqian Zheng (25 matches)", "Riana Soprala (8 matches)", "Laasya Polineni (6 matches)", "Sophia Solo (6 matches)", "Felix Liu (6 matches)"]}