{"name": "Aanya Latne", "gender": "Female", "yob": 2014, "rankings": ["GS U13 #93 (806pts)", "GS U15 #207 (806pts)", "GS U17 #333 (806pts)", "GS U19 #421 (806pts)", "GD U13 #68 (1764pts)", "GD U15 #161 (1764pts)", "GD U17 #279 (1764pts)", "GD U19 #356 (1764pts)", "XD U13 #175 (806pts)", "XD U15 #383 (806pts)", "XD U17 #599 (806pts)", "XD U19 #761 (806pts)"], "career": "7 tournaments, 9-32 (22%)", "progression": ["2025-02-01: GD U13 #81, GS U13 #91, XD U13 #195", "2026-03-01: GD U13 #62, GS U13 #75, XD U13 #145"], "recent": ["                     2024 YONEX MIDWEST ORC 0W-4L", "                     2024 MIDWEST OLC 6W-7L", "                     2025 YONEX MIDWEST ORC 0W-4L", "                     2025 MIDWEST CRC 0W-3L", "                     2025 YONEX U.S. JUNIOR NATIONAL CHAMPIONSHIPS 0W-7L", "                     2025 NE OLC 0W-4L", "                     2025 EGRET MIDWEST OLC 3W-3L"], "titles": [], "runner_ups": ["GD U13 at 2025 EGRET MIDWEST OLC"], "partners": ["Pearl Li (7 matches)", "Luke Wen (4 matches)", "Sasikavi Muthu (4 matches)", "Brayden Liu (3 matches)", "Annabeth Pan (2 matches)"]}