{"name": "Molly Wei", "gender": "Female", "yob": 2014, "rankings": ["GS U13 #56 (1323pts)", "GS U15 #139 (1323pts)", "GS U17 #249 (1323pts)", "GS U19 #331 (1323pts)", "GD U13 #39 (2630pts)", "GD U15 #113 (2630pts)", "GD U17 #219 (2630pts)", "GD U19 #294 (2630pts)", "XD U13 #100 (1445pts)", "XD U15 #254 (1445pts)", "XD U17 #431 (1445pts)", "XD U19 #593 (1445pts)"], "career": "11 tournaments, 23-41 (36%)", "progression": ["2025-02-01: GD U13 #95, GS U13 #101, XD U13 #206", "2026-03-01: GD U13 #37, GS U13 #48, XD U13 #94"], "recent": ["                     2024 YONEX NORCAL ORC 0W-3L", "Jan 17 to Jan 19     2026 YONEX ARENA SOCAL ORC 3W-3L", "Feb 20 to Feb 22     2026 DAVE FREEMAN JR. SOCAL OLC 6W-4L", "                     2025 ABC OLC 1W-3L", "                     2025 CAN-AM NORCAL OLC 2W-6L", "Mar 13 to Mar 15     2026 BINTANG NorCal OLC 0W-3L", "                     2025 YONEX SOCAL ORC 0W-3L", "                     2025 YONEX U.S. JUNIOR NATIONAL CHAMPIONSHIPS 1W-6L", "                     2025 YONEX SYNERGY NORCAL ORC 1W-3L", "                     2025 DAVE FREEMAN JR. SOCAL OLC 5W-5L"], "titles": [], "runner_ups": [], "partners": ["Allen Wu (10 matches)", "Paris Liang (6 matches)", "Riya Prasanna (6 matches)", "Yueran Jiang (3 matches)", "Austin Ren (3 matches)"]}