{"name": "Ivan Jia", "gender": "Male", "yob": 2013, "rankings": ["BS U15 #152 (1284pts)", "BS U17 #279 (1284pts)", "BS U19 #420 (1284pts)", "BD U15 #142 (2158pts)", "BD U17 #280 (2158pts)", "BD U19 #418 (2158pts)", "XD U15 #630 (292pts)", "XD U17 #879 (292pts)", "XD U19 #1041 (292pts)"], "career": "8 tournaments, 13-19 (41%)", "progression": ["2026-03-01: BD U15 #101, BS U15 #109, XD U15 #338"], "recent": ["Feb 14 to Feb 16     2026 YONEX DFW BADMINTON SOUTH ORC 0W-2L", "                     2025 YONEX LIBC NORTHEAST ORC 5W-3L", "                     2025 YONEX MIDWEST ORC 2W-3L", "                     2025 South OLC 1W-2L", "                     2025 CAPITAL NE OLC 2W-2L", "                     2025 YONEX SOUTH ORC 0W-2L", "                     2025 NE OLC 1W-2L", "                     2024 NE CRC 2W-3L"], "titles": [], "runner_ups": [], "partners": ["Tamoghna Aniket Sivadanam (3 matches)", "Benjamin Chen (2 matches)", "Zisheng (GaoGao) Fan (2 matches)", "Sunny Zheng (2 matches)", "Siddhanth Selvanathan (2 matches)"]}