{"name": "Kaie Bernal", "gender": "Male", "yob": 2011, "rankings": ["BS U17 #342 (1053pts)", "BS U19 #486 (1053pts)", "BD U17 #354 (1661pts)", "BD U19 #500 (1661pts)", "XD U19 #523 (1875pts)"], "career": "3 tournaments, 0-10 (0%)", "progression": [], "recent": ["                     2025 South OLC 0W-4L", "                     2025 CAPITAL NE OLC 0W-2L", "                     2025 NE OLC 0W-4L"], "titles": [], "runner_ups": [], "partners": ["Lilyanna Lai (4 matches)", "Michael Li (1 matches)", "Zarnie Htut (1 matches)", "Rushil Reddy Aleti (1 matches)"]}