{
  "usab_id": "522341",
  "date": "2026-01-01",
  "categories": [
    {
      "category": "XD U13",
      "ranking_points": 499,
      "rank": 175,
      "tournaments": [
        {
          "tournament": "2025 EGRET MIDWEST OPEN LOCAL CHAMPIONSHIPS",
          "position": "1",
          "points": "255"
        },
        {
          "tournament": "2025 EGRET MIDWEST CLOSED REGIONAL CHAMPIONSHIPS",
          "position": "5 to 8",
          "points": "159"
        },
        {
          "tournament": "2025 YONEX SPBA MIDWEST OPEN REGIONAL CHAMPIONSHIPS",
          "position": "33-64",
          "points": "85"
        }
      ]
    },
    {
      "category": "GS U13",
      "ranking_points": 672,
      "rank": 75,
      "tournaments": [
        {
          "tournament": "2025 EGRET MIDWEST OPEN LOCAL CHAMPIONSHIPS",
          "position": "1",
          "points": "255"
        },
        {
          "tournament": "2025 YONEX SPBA MIDWEST OPEN REGIONAL CHAMPIONSHIPS",
          "position": "17-32",
          "points": "213"
        },
        {
          "tournament": "2025 EGRET MIDWEST CLOSED REGIONAL CHAMPIONSHIPS",
          "position": "4",
          "points": "204"
        }
      ]
    },
    {
      "category": "GD U13",
      "ranking_points": 685,
      "rank": 84,
      "tournaments": [
        {
          "tournament": "2025 EGRET MIDWEST OPEN LOCAL CHAMPIONSHIPS",
          "position": "1",
          "points": "255"
        },
        {
          "tournament": "2025 EGRET MIDWEST CLOSED REGIONAL CHAMPIONSHIPS",
          "position": "3",
          "points": "217"
        },
        {
          "tournament": "2025 YONEX SPBA MIDWEST OPEN REGIONAL CHAMPIONSHIPS",
          "position": "17-32",
          "points": "213"
        }
      ]
    }
  ],
  "name": "Sarah Xie",
  "year_of_birth": null,
  "gender": "F",
  "year_of_birth_inferred": 2015,
  "year_of_birth_confidence": "confirmed"
}