{
  "usab_id": "1019494",
  "date": "2025-01-01",
  "categories": [
    {
      "category": "XD U19",
      "ranking_points": 30000,
      "rank": 10,
      "tournaments": [
        {
          "tournament": "2024 YONEX U.S. Junior National Championships",
          "position": "2",
          "points": "18000"
        },
        {
          "tournament": "2024 YONEX SOCAL ARENA OPEN REGIONAL CHAMPIONSHIPS & SELECTION EVENT FOR 2024 SHONAI INVITATIONAL",
          "position": "4",
          "points": "8000"
        },
        {
          "tournament": "2024 YONEX FRISCO SOUTH OPEN REGIONAL CHAMPIONSHIPS",
          "position": "9-16",
          "points": "4000"
        }
      ]
    },
    {
      "category": "GS U19",
      "ranking_points": 42500,
      "rank": 2,
      "tournaments": [
        {
          "tournament": "2024 YONEX U.S. Junior National Championships",
          "position": "1",
          "points": "20000"
        },
        {
          "tournament": "2024 YONEX SYNERGY NORCAL OPEN REGIONAL CHAMPIONSHIPS",
          "position": "1",
          "points": "10000"
        },
        {
          "tournament": "2024 YONEX FRISCO SOUTH OPEN REGIONAL CHAMPIONSHIPS",
          "position": "3",
          "points": "8500"
        },
        {
          "tournament": "2024 YONEX SOCAL ARENA OPEN REGIONAL CHAMPIONSHIPS & SELECTION EVENT FOR 2024 SHONAI INVITATIONAL",
          "position": "9-16",
          "points": "4000"
        }
      ]
    },
    {
      "category": "GD U19",
      "ranking_points": 33000,
      "rank": 6,
      "tournaments": [
        {
          "tournament": "2024 YONEX U.S. Junior National Championships",
          "position": "5",
          "points": "15000"
        },
        {
          "tournament": "2024 YONEX SOCAL ARENA OPEN REGIONAL CHAMPIONSHIPS & SELECTION EVENT FOR 2024 SHONAI INVITATIONAL",
          "position": "1",
          "points": "10000"
        },
        {
          "tournament": "2024 YONEX SYNERGY NORCAL OPEN REGIONAL CHAMPIONSHIPS",
          "position": "4",
          "points": "8000"
        }
      ]
    }
  ],
  "name": "Nicole Krawczyk",
  "year_of_birth": null,
  "gender": "F"
}