{
  "usab_id": "530254",
  "date": "2025-05-01",
  "categories": [
    {
      "category": "BS U11",
      "ranking_points": 687,
      "rank": 30,
      "tournaments": [
        {
          "tournament": "2025 SCHAFER SLG SOUTH OPEN LOCAL CHAMPIONSHIPS",
          "position": "2",
          "points": "230"
        },
        {
          "tournament": "2025 YONEX DFW BADMINTON LEWISVILLE SOUTH OPEN REGIONAL CHAMPIONSHIPS & SELECTION EVENT FOR 2025 SHO",
          "position": "17-32",
          "points": "213"
        },
        {
          "tournament": "2025 AUSTIN BADMINTON LEANDER SOUTH CLOSED REGIONAL CHAMPIONSHIPS",
          "position": "5-8",
          "points": "159"
        },
        {
          "tournament": "2025 YONEX ARENA SOCAL OPEN REGIONAL CHAMPIONSHIPS",
          "position": "33-64",
          "points": "85"
        }
      ]
    },
    {
      "category": "BD U11",
      "ranking_points": 744,
      "rank": 45,
      "tournaments": [
        {
          "tournament": "2025 YONEX ARENA SOCAL OPEN REGIONAL CHAMPIONSHIPS",
          "position": "17-32",
          "points": "213"
        },
        {
          "tournament": "2025 YONEX DFW BADMINTON LEWISVILLE SOUTH OPEN REGIONAL CHAMPIONSHIPS & SELECTION EVENT FOR 2025 SHO",
          "position": "17-32",
          "points": "213"
        },
        {
          "tournament": "2025 AUSTIN BADMINTON LEANDER SOUTH CLOSED REGIONAL CHAMPIONSHIPS",
          "position": "5-8",
          "points": "159"
        },
        {
          "tournament": "2025 SCHAFER SLG SOUTH OPEN LOCAL CHAMPIONSHIPS",
          "position": "5-8",
          "points": "159"
        }
      ]
    },
    {
      "category": "XD U11",
      "ranking_points": 687,
      "rank": 52,
      "tournaments": [
        {
          "tournament": "2025 YONEX ARENA SOCAL OPEN REGIONAL CHAMPIONSHIPS",
          "position": "17-32",
          "points": "213"
        },
        {
          "tournament": "2025 YONEX DFW BADMINTON LEWISVILLE SOUTH OPEN REGIONAL CHAMPIONSHIPS & SELECTION EVENT FOR 2025 SHO",
          "position": "17-32",
          "points": "213"
        },
        {
          "tournament": "2025 AUSTIN BADMINTON LEANDER SOUTH CLOSED REGIONAL CHAMPIONSHIPS",
          "position": "5-8",
          "points": "159"
        },
        {
          "tournament": "2025 SCHAFER SLG SOUTH OPEN LOCAL CHAMPIONSHIPS",
          "position": "9-16",
          "points": "102"
        }
      ]
    }
  ],
  "name": "Neel Achari",
  "year_of_birth": null,
  "gender": "M"
}