{
  "usab_id": "1020950",
  "date": "2025-10-01",
  "categories": [
    {
      "category": "XD U17",
      "ranking_points": 8127,
      "rank": 71,
      "tournaments": [
        {
          "tournament": "2025 YONEX BELLEVUE NORTHWEST OPEN REGIONAL CHAMPIONSHIPS",
          "position": "2",
          "points": "4860"
        },
        {
          "tournament": "2024 SGVBC SoCal Closed Regional Championships",
          "position": "3",
          "points": "1377"
        },
        {
          "tournament": "2025 YONEX DFW BADMINTON LEWISVILLE SOUTH OPEN REGIONAL CHAMPIONSHIPS & SELECTION EVENT FOR 2025 SHO",
          "position": "17-32",
          "points": "1350"
        },
        {
          "tournament": "2025 YONEX ARENA SOCAL OPEN REGIONAL CHAMPIONSHIPS",
          "position": "33-64",
          "points": "540"
        },
        {
          "tournament": "2024 YONEX SYNERGY NORCAL OPEN REGIONAL CHAMPIONSHIPS",
          "position": "33-64",
          "points": "540"
        }
      ]
    },
    {
      "category": "GS U19",
      "ranking_points": 4305,
      "rank": 67,
      "tournaments": [
        {
          "tournament": "2024 SGVBC SoCal Closed Regional Championships",
          "position": "5 to 8",
          "points": "1875"
        },
        {
          "tournament": "2025 YONEX BELLEVUE NORTHWEST OPEN REGIONAL CHAMPIONSHIPS",
          "position": "17-32",
          "points": "1350"
        },
        {
          "tournament": "2024 YONEX SYNERGY NORCAL OPEN REGIONAL CHAMPIONSHIPS",
          "position": "33-64",
          "points": "540"
        },
        {
          "tournament": "2025 YONEX ARENA SOCAL OPEN REGIONAL CHAMPIONSHIPS",
          "position": "33-64",
          "points": "540"
        }
      ]
    },
    {
      "category": "GS U17",
      "ranking_points": 2430,
      "rank": 91,
      "tournaments": [
        {
          "tournament": "2025 YONEX BELLEVUE NORTHWEST OPEN REGIONAL CHAMPIONSHIPS",
          "position": "17-32",
          "points": "1350"
        },
        {
          "tournament": "2025 YONEX ARENA SOCAL OPEN REGIONAL CHAMPIONSHIPS",
          "position": "33-64",
          "points": "540"
        },
        {
          "tournament": "2024 YONEX SYNERGY NORCAL OPEN REGIONAL CHAMPIONSHIPS",
          "position": "33-64",
          "points": "540"
        }
      ]
    },
    {
      "category": "GD U19",
      "ranking_points": 13470,
      "rank": 45,
      "tournaments": [
        {
          "tournament": "2024 YONEX SYNERGY NORCAL OPEN REGIONAL CHAMPIONSHIPS",
          "position": "4",
          "points": "4320"
        },
        {
          "tournament": "2025 YONEX DFW BADMINTON LEWISVILLE SOUTH OPEN REGIONAL CHAMPIONSHIPS & SELECTION EVENT FOR 2025 SHO",
          "position": "5 to 8",
          "points": "3375"
        },
        {
          "tournament": "2025 YONEX ARENA SOCAL OPEN REGIONAL CHAMPIONSHIPS",
          "position": "5 to 8",
          "points": "3375"
        },
        {
          "tournament": "2024 SGVBC SoCal Closed Regional Championships",
          "position": "4",
          "points": "2400"
        },
        {
          "tournament": "2025 YONEX BELLEVUE NORTHWEST OPEN REGIONAL CHAMPIONSHIPS",
          "position": "9 to 16",
          "points": "2160"
        }
      ]
    },
    {
      "category": "GD U17",
      "ranking_points": 13230,
      "rank": 22,
      "tournaments": [
        {
          "tournament": "2024 YONEX SYNERGY NORCAL OPEN REGIONAL CHAMPIONSHIPS",
          "position": "4",
          "points": "4320"
        },
        {
          "tournament": "2025 YONEX ARENA SOCAL OPEN REGIONAL CHAMPIONSHIPS",
          "position": "5 to 8",
          "points": "3375"
        },
        {
          "tournament": "2025 YONEX DFW BADMINTON LEWISVILLE SOUTH OPEN REGIONAL CHAMPIONSHIPS & SELECTION EVENT FOR 2025 SHO",
          "position": "5 to 8",
          "points": "3375"
        },
        {
          "tournament": "2025 YONEX BELLEVUE NORTHWEST OPEN REGIONAL CHAMPIONSHIPS",
          "position": "9 to 16",
          "points": "2160"
        }
      ]
    }
  ],
  "name": "Maggie Zang",
  "year_of_birth": null,
  "gender": "F",
  "year_of_birth_inferred": 2010,
  "year_of_birth_confidence": "confirmed"
}