{
  "usab_id": "1022001",
  "date": "2025-03-01",
  "categories": [
    {
      "category": "XD U19",
      "ranking_points": 4275,
      "rank": 138,
      "tournaments": [
        {
          "tournament": "2024 NE NJBC Closed Regional Championships",
          "position": "4",
          "points": "2400"
        },
        {
          "tournament": "2024 NJBC NE CRC",
          "position": "5 to 8",
          "points": "1875"
        }
      ]
    },
    {
      "category": "GS U19",
      "ranking_points": 2550,
      "rank": 82,
      "tournaments": [
        {
          "tournament": "2024 NE NJBC Closed Regional Championships",
          "position": "3",
          "points": "2550"
        }
      ]
    }
  ],
  "name": "Kishita Arora",
  "year_of_birth": null,
  "gender": "XD"
}